{
    "pop": 4241,
    "electronic": 2506,
    "dance": 2446,
    "indie": 1910,
    "hip-hop": 1298,
    "rock": 1232,
    "rap": 1150,
    "house": 1142,
    "soul": 982,
    "alternative": 963,
    "poptron": 709,
    "indie rock": 622,
    "new wave": 442,
    "electropop": 432,
    "hip hop": 431,
    "synthpop": 428,
    "rnb": 423,
    "trap": 411,
    "psychedelic": 389,
    "dance-pop": 358,
    "british": 344,
    "indie pop": 335,
    "katy perry": 314,
    "disco": 284,
    "dancehall": 262,
    "pop rap": 241,
    "electroclash": 239,
    "deep house": 233,
    "lady gaga": 208,
    "fetty wap": 205,
    "reggae": 200,
    "pop rock": 199,
    "adele": 198,
    "emo rap": 181,
    "party": 179,
    "bassline": 166,
    "art pop": 154,
    "tropical house": 153,
    "epic": 147,
    "edm": 143,
    "jazz": 139,
    "europa plus": 133,
    "club": 132,
    "indietronica": 131,
    "kanye west": 129,
    "drake": 129,
    "romantic": 118,
    "classic rock": 118,
    "rihanna": 109,
    "timbaland": 106,
    "soundtrack": 105,
    "sade": 104,
    "oldies": 100,
    "bubblegum bass": 100,
    "bedroom pop": 100,
    "alessia cara": 100,
    "grime": 100,
    "daptone": 100,
    "dansk": 100,
    "travis scott": 100,
    "breakbeat": 100,
    "tech house": 100,
    "sza": 100,
    "riot grrrl": 100,
    "big band": 100,
    "pop soul": 100,
    "classic tracks": 100,
    "chill house": 100,
    "kyla": 100,
    "eurythmics": 100,
    "dnb": 100,
    "dua lipa": 100,
    "new rave": 100,
    "folk": 100,
    "uk garage": 95,
    "akon": 90,
    "techno": 84,
    "latin": 81,
    "gorillaz": 80,
    "swedish": 76,
    "glam rock": 75,
    "hyperpop": 74,
    "french": 74,
    "australian": 72,
    "post-punk": 70,
    "alt-pop": 67,
    "bmson": 66,
    "skweee": 66,
    "garage": 66,
    "future funk": 66,
    "diverse": 66,
    "meme": 66,
    "pop edm": 66,
    "kendrick lamar": 66,
    "disco house": 66,
    "witch house": 66,
    "wizkid": 66,
    "gangsta rap": 66,
    "eurodance": 65,
    "ellie goulding": 61,
    "love": 59,
    "drum and bass": 58,
    "electronica": 50,
    "piano": 48,
    "electro house": 46,
    "funk": 44,
    "peter": 44,
    "funky house": 43,
    "electro": 43,
    "new jack swing": 42,
    "sean paul": 42,
    "jersey club": 42,
    "hard rock": 41,
    "go-go": 37,
    "remix": 37,
    "david guetta": 37,
    "james bond": 36,
    "post-rock": 35,
    "dance-punk": 34,
    "industrial": 34,
    "flop": 33,
    "moombahton": 33,
    "vladivostok fm": 33,
    "ballad": 33,
    "synth-pop": 33,
    "migos": 33,
    "french house": 32,
    "emo": 32,
    "soft rock": 30,
    "britney spears": 30,
    "logic": 29,
    "southern rock": 29,
    "big beat": 29,
    "cover": 29,
    "funky": 29,
    "horny": 29,
    "fun": 28,
    "new romantic": 27,
    "reggaeton": 26,
    "easy listening": 25,
    "cloud rap": 25,
    "night": 25,
    "trance": 25,
    "sexy": 25,
    "bee gees": 25,
    "speed garage": 24,
    "zara larsson": 24,
    "kings of leon": 22,
    "cyndi lauper": 20,
    "poland": 20,
    "polish": 20,
    "balearic beat": 19,
    "kanye": 17,
    "chill": 17,
    "melancholy": 17,
    "futurepop": 17,
    "indie folk": 17,
    "daft punk": 16,
    "catchy": 16,
    "happy": 16,
    "nice": 16,
    "upbeat lyrics": 16,
    "c major": 16,
    "swing": 16,
    "blues": 16,
    "baggy": 15,
    "chillstep": 15,
    "nicki minaj": 15,
    "agartha": 15,
    "nu-disco": 15,
    "indie sleaze": 15,
    "female vocals": 14,
    "uk street soul": 14,
    "the police": 14,
    "dope shit": 13,
    "smack that": 13,
    "punk": 12,
    "bitpop": 12,
    "baltimore club": 12,
    "saxophone": 12,
    "justin bieber": 11,
    "chillout": 11,
    "canadian": 10,
    "kick": 10,
    "personal": 10,
    "fleeting": 10,
    "goat": 10,
    "just dance": 10,
    "saltburn": 10,
    "ratchet music": 10,
    "hino": 9,
    "summer": 9,
    "hipster indie": 9,
    "firework": 9,
    "frankie valli": 8,
    "vinnie": 8,
    "victor": 8,
    "power": 8,
    "uk number one": 8,
    "hype": 8,
    "american": 8,
    "uk hip-hop": 8,
    "uk rap": 8,
    "dubstep": 8,
    "synth funk": 8,
    "vibes": 8,
    "calypso": 8,
    "beautiful": 8,
    "smooth": 8,
    "taylor dayne": 8,
    "ballin": 8,
    "remy boyz": 8,
    "le tigre": 8,
    "motown sound": 8,
    "vocal trance": 8,
    "nerdcore": 8,
    "fnaf": 8,
    "unlove": 8,
    "roar": 8,
    "amy winehouse": 8,
    "big music": 8,
    "melancholic": 7,
    "teenage dream": 7,
    "whistling": 7,
    "smooth jazz": 7,
    "shakira": 7,
    "the way i are": 7,
    "a reggae feel": 7,
    "arctic monkeys": 6,
    "gossip girl": 6,
    "shoegaze": 6,
    "experimental": 5,
    "jet": 5,
    "powerful": 5,
    "euro house": 5,
    "diva house": 5,
    "synth pop": 5,
    "toxic": 5,
    "toto": 5,
    "duo": 4,
    "sad": 4,
    "omg": 4,
    "tame impala": 4,
    "ice spice": 4,
    "english": 4,
    "a-ha": 4,
    "chumbawamba": 4,
    "lupe fiasco": 4,
    "for aerobics": 4,
    "power pop": 4,
    "alejandro": 4,
    "new order": 4,
    "tropical": 4,
    "acid house": 4,
    "up tempo": 4
}