{
    "electronic": 1152,
    "dance": 1064,
    "indie": 1034,
    "pop": 988,
    "rock": 775,
    "house": 745,
    "hip-hop": 736,
    "soul": 700,
    "disco": 514,
    "indie rock": 465,
    "alternative": 425,
    "rap": 334,
    "funk": 331,
    "rnb": 292,
    "deep house": 270,
    "indie pop": 258,
    "poptron": 239,
    "pop rock": 213,
    "electropop": 205,
    "new wave": 204,
    "edm": 195,
    "uk garage": 189,
    "dance-pop": 172,
    "pop rap": 170,
    "hip hop": 162,
    "jazz": 158,
    "synthpop": 150,
    "alt-pop": 137,
    "bassline": 133,
    "british": 118,
    "industrial": 115,
    "classic rock": 108,
    "party": 106,
    "kanye west": 104,
    "power pop": 104,
    "riot grrrl": 100,
    "pop soul": 100,
    "big band": 100,
    "coldwave": 100,
    "chill house": 100,
    "europa plus": 100,
    "electro swing": 100,
    "dire straits": 100,
    "tech house": 100,
    "eurythmics": 100,
    "nu metal": 100,
    "dnb": 100,
    "sophisti-pop": 100,
    "post-grunge": 100,
    "classic tracks": 100,
    "psychedelic": 100,
    "timbaland": 100,
    "swedish": 96,
    "techno": 93,
    "experimental": 77,
    "gorillaz": 66,
    "club": 66,
    "garage": 66,
    "funky house": 66,
    "future funk": 66,
    "pop edm": 66,
    "bedroom pop": 66,
    "pink": 66,
    "drum and bass": 58,
    "eurodance": 57,
    "idm": 56,
    "electronica": 55,
    "linkin park": 51,
    "oldies": 50,
    "post-punk": 44,
    "electro-swing": 44,
    "noided": 43,
    "acid jazz": 42,
    "catchy": 40,
    "go-go": 37,
    "motown": 35,
    "australian": 35,
    "summer": 35,
    "love": 35,
    "nelly": 35,
    "upti": 33,
    "funk lift off": 33,
    "garage rock": 33,
    "blues": 32,
    "big beat": 29,
    "cover": 29,
    "happy": 28,
    "amy winehouse": 26,
    "swing": 25,
    "trance": 25,
    "speed garage": 24,
    "zara larsson": 24,
    "hard rock": 22,
    "daft punk": 21,
    "arctic monkeys": 20,
    "my top songs": 18,
    "kick": 17,
    "kato": 16,
    "fun": 16,
    "woman": 16,
    "yes": 16,
    "balearic beat": 15,
    "baggy": 15,
    "agartha": 15,
    "death grips": 14,
    "french": 11,
    "electroclash": 10,
    "metal": 10,
    "adele": 9,
    "crazy": 9,
    "le tigre": 8,
    "motown sound": 8,
    "vinnie": 8,
    "victor": 8,
    "soft rock": 8,
    "techhouse": 8,
    "chris martin": 8,
    "power": 8,
    "smooth": 8,
    "the police": 8,
    "art pop": 8,
    "spoken-word": 8,
    "synth-pop": 8,
    "kings of leon": 7,
    "whistling": 7,
    "the way i are": 7,
    "gnarls barkley": 6,
    "rapcore": 6,
    "saxophone": 5,
    "jamiroquai": 5,
    "funky": 5,
    "chicago": 5,
    "synth funk": 4,
    "tame impala": 4,
    "male vocals": 4,
    "duo": 4,
    "darkwave": 4,
    "furry": 4,
    "lupe fiasco": 4,
    "paramore": 4
}