{
    "pop": 978,
    "indie": 869,
    "electronic": 685,
    "rock": 619,
    "hip-hop": 533,
    "rap": 527,
    "dance": 510,
    "electropop": 457,
    "poptron": 400,
    "alternative": 393,
    "classic rock": 351,
    "rnb": 295,
    "psychedelic": 291,
    "synthpop": 274,
    "indie rock": 273,
    "folk": 196,
    "hip hop": 194,
    "indie pop": 182,
    "metal": 173,
    "soul": 173,
    "house": 140,
    "funk": 117,
    "electroclash": 111,
    "pop rock": 108,
    "soft rock": 108,
    "pop rap": 108,
    "future bass": 100,
    "mood ring": 100,
    "slow disco": 100,
    "reggae": 100,
    "electro swing": 100,
    "tech house": 100,
    "edm": 100,
    "fetty wap": 100,
    "lush": 100,
    "bedroom pop": 100,
    "trap": 100,
    "bubblegum bass": 100,
    "lana del rey": 100,
    "city pop": 100,
    "witch house": 95,
    "electro house": 92,
    "art pop": 89,
    "dance-pop": 84,
    "hyperpop": 83,
    "surf rock": 71,
    "british": 67,
    "lewiscore": 66,
    "hard rock": 66,
    "heavy metal": 66,
    "pop edm": 66,
    "chill": 66,
    "minimal pop": 64,
    "new wave": 61,
    "dream pop": 44,
    "electro-swing": 44,
    "australian": 43,
    "acid jazz": 42,
    "jersey club": 42,
    "new jack swing": 42,
    "disco": 41,
    "love": 37,
    "downtempo": 36,
    "swedish": 36,
    "happy": 35,
    "black sabbath": 33,
    "metallica": 33,
    "megadeth": 33,
    "rihanna": 33,
    "my spotify": 33,
    "french house": 31,
    "folk rock": 31,
    "drum and bass": 29,
    "dreamrave": 29,
    "kanye west": 27,
    "indie folk": 27,
    "tiffany": 26,
    "trip hop": 25,
    "japanese": 25,
    "olivia": 24,
    "alt-pop": 23,
    "lenny kravitz": 22,
    "ambient pop": 19,
    "phil collins": 19,
    "electronica": 18,
    "synth": 17,
    "saxophone": 17,
    "the weeknd": 17,
    "futurepop": 16,
    "swing": 16,
    "elton john": 16,
    "roses gabor": 16,
    "shaun ryder": 16,
    "yes": 16,
    "gorillaz": 14,
    "big mountain": 14,
    "my top songs": 12,
    "bitpop": 12,
    "baltimore club": 12,
    "uk garage": 12,
    "summer": 10,
    "classic tracks": 10,
    "slipknot": 10,
    "french": 10,
    "duet": 10,
    "daft punk": 9,
    "hipster indie": 9,
    "dutch house": 8,
    "electro": 8,
    "eurodance": 8,
    "vocal trance": 8,
    "american": 8,
    "catchy": 8,
    "hype": 8,
    "hip-hop stuff": 8,
    "bops": 8,
    "all": 8,
    "hypnagogic pop": 8,
    "sophisti-pop": 8,
    "sax": 8,
    "experimental": 7,
    "kings of leon": 7,
    "whistling": 7,
    "arctic monkeys": 6,
    "cover": 6,
    "elo": 5,
    "imogen heap": 5,
    "jamiroquai": 5,
    "funky": 5,
    "chris brown": 5,
    "indietronica": 4,
    "driving": 4,
    "mellow": 4,
    "complextro": 4,
    "reggae-pop": 4,
    "furry": 4,
    "lupe fiasco": 4,
    "weed": 4,
    "mac miller": 4,
    "grunge": 4,
    "ice spice": 4,
    "party": 4,
    "covers": 4
}