{
    "pop": 4343,
    "dance": 2276,
    "electronic": 1869,
    "rock": 1610,
    "indie": 1083,
    "house": 1059,
    "hip-hop": 924,
    "rnb": 805,
    "alternative": 746,
    "rap": 700,
    "indie rock": 580,
    "pop rock": 561,
    "electropop": 539,
    "hip hop": 508,
    "soul": 498,
    "party": 437,
    "dance-pop": 388,
    "new wave": 378,
    "poptron": 347,
    "electroclash": 300,
    "pop rap": 298,
    "synthpop": 285,
    "k-pop": 264,
    "psychedelic": 257,
    "classic rock": 233,
    "deep house": 224,
    "british": 205,
    "trip-hop": 200,
    "edm": 197,
    "indie pop": 196,
    "bubblegum bass": 183,
    "dancehall": 170,
    "bassline": 166,
    "disco": 151,
    "ne-yo": 146,
    "trap": 141,
    "tropical house": 140,
    "kpop": 127,
    "rihanna": 126,
    "summer": 123,
    "reggae": 121,
    "melancholy": 117,
    "baggy": 115,
    "epic": 113,
    "chillout": 112,
    "taio cruz": 111,
    "david guetta": 110,
    "soft rock": 105,
    "techno": 104,
    "power pop": 104,
    "colors": 100,
    "color": 100,
    "breakbeat": 100,
    "coldwave": 100,
    "tech house": 100,
    "new romantic": 100,
    "drake": 100,
    "kyla": 100,
    "oldies": 100,
    "grime": 100,
    "lush": 100,
    "nu metal": 100,
    "cult": 100,
    "dream pop": 100,
    "jade": 100,
    "afrojack": 100,
    "soulja boy": 100,
    "witch house": 95,
    "latin": 93,
    "hyperpop": 87,
    "justin bieber": 84,
    "nu-disco": 81,
    "emo rap": 81,
    "bruno mars": 81,
    "gorillaz": 80,
    "chillwave": 77,
    "synth funk": 74,
    "kanye west": 73,
    "soundtrack": 67,
    "dubstep": 67,
    "colour": 66,
    "colours": 66,
    "chill": 66,
    "pop edm": 66,
    "future funk": 66,
    "avicii": 66,
    "my top songs": 66,
    "wizkid": 66,
    "fleetwood mac": 66,
    "drum and bass": 66,
    "bmson": 66,
    "skweee": 66,
    "vocal": 66,
    "britney spears": 65,
    "electro house": 64,
    "kick": 64,
    "love": 61,
    "romantic": 58,
    "downtempo": 57,
    "nelly": 53,
    "korean": 52,
    "indietronica": 52,
    "linkin park": 51,
    "catchy": 49,
    "electronica": 48,
    "post-punk": 48,
    "eletronic": 48,
    "britpop": 48,
    "acid techno": 45,
    "crunk": 45,
    "adele": 42,
    "jersey club": 42,
    "trip hop": 41,
    "happy": 41,
    "jessie j": 41,
    "uk garage": 37,
    "funk": 36,
    "american": 35,
    "post-rock": 35,
    "dance-punk": 34,
    "balearic beat": 34,
    "sean paul": 34,
    "industrial": 34,
    "synthwave": 33,
    "my spotify": 33,
    "moombahton": 33,
    "glam rock": 33,
    "sunshine pop": 33,
    "piano rock": 33,
    "spoken": 33,
    "instrumental": 33,
    "alt-pop": 33,
    "country": 33,
    "emo": 32,
    "abba": 32,
    "rick and morty": 32,
    "the sopranos": 32,
    "daft punk": 31,
    "french house": 31,
    "speed garage": 29,
    "pop reggae": 29,
    "big beat": 29,
    "fun": 27,
    "countrystep": 27,
    "miley cyrus": 26,
    "male vocalists": 26,
    "dynamite": 26,
    "the killers": 26,
    "electro": 24,
    "one hit wonder": 23,
    "pitbull": 23,
    "sexy": 21,
    "usher": 21,
    "futurepop": 20,
    "pop punk": 20,
    "easy listening": 20,
    "reggaeton": 19,
    "dance pop": 17,
    "ballad": 17,
    "kanye": 17,
    "merengue": 17,
    "bedroom pop": 17,
    "kendrick lamar": 16,
    "yes": 16,
    "french": 15,
    "frutiger aero": 15,
    "ed sheeran": 15,
    "robin schulz": 15,
    "boogie": 15,
    "uk street soul": 14,
    "arctic monkeys": 13,
    "punk": 12,
    "mika": 12,
    "bitpop": 12,
    "baltimore club": 12,
    "future bass": 12,
    "swedish": 11,
    "boogie rock": 10,
    "moderate": 10,
    "canadian": 10,
    "shrek": 10,
    "dark": 10,
    "flo rida": 9,
    "vocal trance": 8,
    "eurodance": 8,
    "cloud rap": 8,
    "hey": 8,
    "workout": 8,
    "fav": 8,
    "eurovision": 8,
    "aviciiforever": 8,
    "nicky romero": 8,
    "lazy": 8,
    "folk": 8,
    "frankie valli": 8,
    "uk hip-hop": 8,
    "uk rap": 8,
    "beautiful": 8,
    "sad": 8,
    "blue": 8,
    "victor": 8,
    "vinnie": 8,
    "garage": 8,
    "estelle": 7,
    "kings of leon": 7,
    "queen": 7,
    "melancholic": 7,
    "shakira": 7,
    "calvin harris": 6,
    "rapcore": 6,
    "metal": 6,
    "shoegaze": 6,
    "gossip girl": 6,
    "complextro": 5,
    "experimental": 5,
    "piano": 5,
    "powerful": 5,
    "toxic": 5,
    "disney": 5,
    "imogen heap": 5,
    "max martin": 5,
    "toto": 5,
    "american boy": 4,
    "darkwave": 4,
    "duo": 4,
    "acoustic": 4,
    "tame impala": 4,
    "art pop": 4,
    "weed": 4,
    "mac miller": 4,
    "house md": 4,
    "new order": 4,
    "paramore": 4,
    "ice spice": 4,
    "fire": 4,
    "english": 4,
    "tearout": 4,
    "dirty south": 4,
    "up tempo": 4
}