{
    "indie": 457,
    "dance": 449,
    "house": 355,
    "electronic": 336,
    "rock": 302,
    "rap": 269,
    "pop": 249,
    "indie rock": 202,
    "poptron": 200,
    "alternative": 149,
    "electropop": 148,
    "alessia cara": 100,
    "phonk": 100,
    "deep house": 100,
    "britpop": 100,
    "nu metal": 100,
    "rally house": 100,
    "trap": 100,
    "indie folk": 100,
    "americana": 100,
    "psychedelic": 90,
    "soul": 87,
    "synthpop": 78,
    "indie pop": 72,
    "techno": 67,
    "garage": 66,
    "club": 66,
    "british": 59,
    "eurodance": 57,
    "linkin park": 52,
    "hip-hop": 50,
    "hip hop": 45,
    "industrial": 34,
    "funky house": 33,
    "edm": 33,
    "logic": 29,
    "driving": 29,
    "folk": 29,
    "big beat": 29,
    "kick": 27,
    "catchy": 26,
    "summer": 26,
    "pop rock": 26,
    "keane": 22,
    "electronica": 21,
    "swedish": 20,
    "woman": 17,
    "rnb": 17,
    "piano": 15,
    "spring": 15,
    "happy": 12,
    "daft punk": 9,
    "techhouse": 8,
    "pop rap": 8,
    "divertido": 8,
    "western": 8,
    "canada": 8,
    "kings of leon": 7,
    "australian": 6,
    "arctic monkeys": 6,
    "french": 6,
    "domino": 6,
    "jessie j": 6,
    "rapcore": 6,
    "metal": 5,
    "sad": 4,
    "in love": 4
}