{
    "pop": 2535,
    "electronic": 2392,
    "dance": 1807,
    "house": 1118,
    "electropop": 1012,
    "hip-hop": 992,
    "indie": 968,
    "rock": 778,
    "rnb": 577,
    "dance-pop": 567,
    "poptron": 555,
    "alternative": 548,
    "rap": 539,
    "electro house": 407,
    "soul": 395,
    "synthpop": 373,
    "indie rock": 332,
    "hip hop": 320,
    "uk garage": 268,
    "pop rap": 253,
    "bassline": 251,
    "new wave": 204,
    "electroclash": 203,
    "deep house": 200,
    "reggae": 200,
    "funk": 198,
    "classic rock": 179,
    "pop rock": 169,
    "dire straits": 166,
    "indie pop": 154,
    "jersey club": 142,
    "british": 140,
    "eurodance": 133,
    "trip-hop": 133,
    "party": 132,
    "experimental": 126,
    "psychedelic": 119,
    "disco": 118,
    "chillout": 113,
    "trance": 104,
    "coldwave": 100,
    "jay-z": 100,
    "alicia keys": 100,
    "post-grunge": 100,
    "power pop": 100,
    "motown": 100,
    "riot grrrl": 100,
    "nu metal": 100,
    "eurovision": 100,
    "skweee": 100,
    "trap": 100,
    "french electro": 100,
    "bubblegum bass": 100,
    "classic tracks": 100,
    "slow disco": 100,
    "city pop": 100,
    "chill": 92,
    "club": 91,
    "kanye west": 89,
    "cloud rap": 85,
    "latin": 83,
    "hyperpop": 83,
    "david guetta": 80,
    "techno": 75,
    "rihanna": 75,
    "garage house": 74,
    "witch house": 70,
    "big beat": 69,
    "future funk": 66,
    "disco house": 66,
    "pink": 66,
    "garage": 66,
    "french house": 66,
    "lol": 66,
    "speed garage": 66,
    "lewiscore": 66,
    "fidget house": 66,
    "acid house": 65,
    "edm": 62,
    "hard rock": 59,
    "indietronica": 56,
    "bass house": 56,
    "dub": 54,
    "post-punk": 51,
    "gorillaz": 51,
    "linkin park": 51,
    "electronica": 48,
    "electro": 46,
    "australian": 45,
    "dream pop": 44,
    "noided": 43,
    "future garage": 42,
    "chillwave": 41,
    "dutch house": 41,
    "jackin house": 41,
    "jessie j": 41,
    "jennifer lopez": 39,
    "neo-soul": 38,
    "beyonce": 36,
    "romanian": 36,
    "nelly": 35,
    "shaggy": 34,
    "industrial": 34,
    "my top songs": 33,
    "vladivostok fm": 33,
    "indie soul": 33,
    "calm": 33,
    "funky house": 33,
    "mood ring": 33,
    "bloghouse": 33,
    "new rave": 33,
    "gwen stefani": 32,
    "new romantic": 30,
    "remix": 29,
    "drum and bass": 29,
    "driving": 29,
    "downtempo": 29,
    "florence welch": 27,
    "britpop": 26,
    "male vocalists": 26,
    "nicki minaj": 25,
    "electrorock": 25,
    "alt-pop": 24,
    "balearic beat": 23,
    "happy": 21,
    "complextro": 17,
    "futurepop": 17,
    "nice": 17,
    "elton john": 16,
    "love": 15,
    "bon jovi": 15,
    "boogie": 15,
    "summer": 14,
    "big mountain": 14,
    "fun": 13,
    "midtempo bass": 13,
    "uk bass": 12,
    "miami bass": 12,
    "bitpop": 12,
    "baltimore club": 12,
    "europop": 12,
    "cool": 11,
    "electonic": 11,
    "japanese": 11,
    "duet": 10,
    "madonna": 10,
    "c major": 10,
    "lily allen": 9,
    "ace of base": 9,
    "daft punk": 9,
    "payphone": 9,
    "tlc": 9,
    "soft rock": 8,
    "uk number one": 8,
    "synth pop": 8,
    "filler": 8,
    "diva house": 8,
    "cunty": 8,
    "baggy": 8,
    "power": 8,
    "le tigre": 8,
    "esc": 8,
    "outkast": 8,
    "synthwave": 8,
    "vocal trance": 8,
    "nerdcore": 8,
    "fnaf": 8,
    "kings of leon": 7,
    "cowbell": 7,
    "dream trance": 7,
    "oldies": 7,
    "swedish": 7,
    "groove": 7,
    "dancehall": 7,
    "jazz-funk": 7,
    "arctic monkeys": 6,
    "ambient": 6,
    "french": 6,
    "rapcore": 6,
    "metal": 6,
    "chris brown": 5,
    "saxophone": 5,
    "breakbeat": 5,
    "darkwave": 4,
    "duo": 4,
    "post-dubstep": 4,
    "ice spice": 4,
    "english": 4,
    "reggae-pop": 4,
    "hair metal": 4,
    "dance pop": 4,
    "lupe fiasco": 4,
    "trip hop": 4,
    "house md": 4,
    "lo-fi": 4,
    "russian": 4,
    "cold wave": 4
}