{
    "rock": 855,
    "dance": 426,
    "classic rock": 425,
    "soul": 380,
    "pop": 358,
    "hip-hop": 300,
    "electronic": 268,
    "indie": 220,
    "house": 208,
    "psychedelic": 200,
    "metal": 200,
    "alternative": 152,
    "rap": 144,
    "hard rock": 139,
    "jazz": 137,
    "british": 114,
    "hip hop": 112,
    "indie rock": 106,
    "kanye west": 101,
    "hyperpop": 100,
    "poptron": 100,
    "edm": 100,
    "tech house": 100,
    "instrumental": 100,
    "sad": 100,
    "zara larsson": 100,
    "bassline": 100,
    "glam rock": 100,
    "australian": 100,
    "epic": 95,
    "new wave": 94,
    "funk": 93,
    "industrial": 81,
    "dance-pop": 80,
    "heavy metal": 66,
    "pop edm": 66,
    "melancholy": 66,
    "hopeful": 66,
    "indie pop": 65,
    "love": 64,
    "sade": 47,
    "disco": 45,
    "pick n mix": 44,
    "pop rock": 42,
    "coldplay": 40,
    "french": 38,
    "synthpop": 36,
    "post-rock": 35,
    "electropop": 33,
    "black sabbath": 33,
    "megadeth": 33,
    "metallica": 33,
    "desperate": 33,
    "minimalism": 33,
    "fav": 33,
    "garage rock": 33,
    "french house": 32,
    "electro": 26,
    "rnb": 25,
    "speed garage": 24,
    "party": 24,
    "piano rock": 16,
    "yes": 16,
    "soft rock": 15,
    "death grips": 14,
    "bryan adams": 12,
    "chillout": 11,
    "slipknot": 10,
    "billy idol": 10,
    "viva la vida": 10,
    "floaty": 10,
    "steady": 10,
    "eurodance": 10,
    "emo rap": 8,
    "catchy": 8,
    "beautiful": 8,
    "canadian": 8,
    "french electro": 8,
    "nu-disco": 8,
    "diane warren": 8,
    "third": 8,
    "fourth": 8,
    "cowbell": 7,
    "yacht rock": 7,
    "kings of leon": 7,
    "pop rap": 7,
    "gossip girl": 6,
    "shoegaze": 6,
    "punk rock": 6,
    "britpop": 6,
    "my top songs": 6,
    "smooth jazz": 6,
    "power pop": 5,
    "queen": 5,
    "king of pop": 5,
    "uk garage": 5,
    "easy listening": 5,
    "nu metal": 4,
    "trap": 4,
    "american": 4
}