{
    "pop": 1768,
    "indie": 1394,
    "hip-hop": 1182,
    "dance": 985,
    "electronic": 902,
    "rock": 884,
    "rap": 789,
    "alternative": 694,
    "trap": 539,
    "poptron": 496,
    "house": 470,
    "rnb": 459,
    "indie rock": 452,
    "electropop": 380,
    "psychedelic": 360,
    "hip hop": 351,
    "dance-pop": 346,
    "disco": 284,
    "soul": 274,
    "edm": 262,
    "new wave": 255,
    "indie pop": 236,
    "pop rap": 208,
    "deep house": 204,
    "classic rock": 192,
    "folk": 174,
    "bassline": 166,
    "electroclash": 143,
    "swedish": 143,
    "funk": 139,
    "party": 129,
    "kanye west": 129,
    "synthpop": 120,
    "uk street soul": 114,
    "fetty wap": 105,
    "bubblegum bass": 100,
    "mood ring": 100,
    "dansk": 100,
    "travis scott": 100,
    "daptone": 100,
    "sza": 100,
    "riot grrrl": 100,
    "breakbeat": 100,
    "classic tracks": 100,
    "coldwave": 100,
    "dire straits": 100,
    "tech house": 100,
    "eurythmics": 100,
    "future": 100,
    "britpop": 100,
    "k-pop": 100,
    "dnb": 100,
    "downtempo": 100,
    "trip hop": 100,
    "pop soul": 100,
    "big band": 100,
    "uk garage": 98,
    "drum and bass": 95,
    "katy perry": 95,
    "akon": 90,
    "british": 85,
    "experimental": 82,
    "emo rap": 81,
    "hyperpop": 74,
    "indietronica": 74,
    "rihanna": 72,
    "french": 69,
    "meme": 66,
    "diverse": 66,
    "witch house": 66,
    "garage": 66,
    "club": 66,
    "kendrick lamar": 66,
    "future funk": 66,
    "pop edm": 66,
    "gorillaz": 66,
    "alt-pop": 64,
    "lady gaga": 64,
    "australian": 60,
    "jungle": 56,
    "indie folk": 55,
    "post-punk": 48,
    "gangsta rap": 44,
    "noided": 43,
    "cloud rap": 40,
    "dancehall": 38,
    "future garage": 37,
    "go-go": 37,
    "motown": 35,
    "nelly": 35,
    "zara larsson": 34,
    "dance-punk": 34,
    "funky house": 33,
    "flop": 33,
    "skweee": 33,
    "emo": 32,
    "french house": 32,
    "drake": 29,
    "uk hip hop": 29,
    "cover": 29,
    "tropical house": 25,
    "night": 25,
    "love": 25,
    "latin": 25,
    "speed garage": 24,
    "keane": 22,
    "electro": 21,
    "electronica": 20,
    "balearic beat": 19,
    "epic": 18,
    "chill": 17,
    "kanye": 17,
    "hulej pidoras": 17,
    "kpop": 17,
    "fun": 16,
    "futurepop": 16,
    "chillout": 16,
    "yes": 16,
    "chicago drill": 15,
    "baggy": 15,
    "agartha": 15,
    "nu-disco": 15,
    "pop rock": 14,
    "icelandic": 14,
    "the police": 14,
    "dope shit": 13,
    "smack that": 13,
    "punk": 12,
    "indie sleaze": 10,
    "personal": 10,
    "duet": 10,
    "hino": 9,
    "summer": 9,
    "techno": 9,
    "crazy": 9,
    "hipster indie": 9,
    "sexy": 9,
    "happy": 9,
    "victor": 8,
    "vinnie": 8,
    "vocal trance": 8,
    "eurodance": 8,
    "power": 8,
    "vibes": 8,
    "calypso": 8,
    "smooth": 8,
    "le tigre": 8,
    "hype": 8,
    "catchy": 8,
    "american": 8,
    "synth funk": 8,
    "uk number one": 8,
    "vocal": 8,
    "trip-hop": 8,
    "motown sound": 8,
    "kings of leon": 7,
    "daft punk": 7,
    "yacht rock": 7,
    "soft rock": 7,
    "arctic monkeys": 6,
    "justin bieber": 6,
    "gnarls barkley": 6,
    "bonehead": 6,
    "heil hitler": 6,
    "jet": 5,
    "chris brown": 5,
    "saxophone": 5,
    "english": 4,
    "chumbawamba": 4,
    "art pop": 4,
    "duo": 4,
    "darkwave": 4,
    "grunge": 4,
    "wave": 4,
    "folk rock": 4,
    "flute": 4,
    "tame impala": 4,
    "lupe fiasco": 4,
    "alejandro": 4,
    "new order": 4,
    "grey": 4
}